setup.py
python_wellrested.egg-info/PKG-INFO
python_wellrested.egg-info/SOURCES.txt
python_wellrested.egg-info/dependency_links.txt
python_wellrested.egg-info/requires.txt
python_wellrested.egg-info/top_level.txt
wellrested/__init__.py
wellrested/connections/__init__.py