Metadata-Version: 1.0
Name: python-wellrested
Version: 0.1.1
Summary: A REST client providing a convenience wrapper over httplib2
Home-page: http://github.com/nowells/python-wellrested/
Author: Nowell Strite
Author-email: nowell@strite.org
License: UNKNOWN
Platform: UNKNOWN
